xai_inference_engine/__init__.py
xai_inference_engine/xai_inference_engine.py
xai_inference_engine/services/__init__.py
xai_inference_engine/services/fm_g_cam.py
xai_inference_engine/utils/__init__.py
xai_inference_engine/utils/grad_utils.py
xai_inference_engine/utils/image_utils.py
xai_inference_engine-0.1.4.dist-info/LICENSE
xai_inference_engine-0.1.4.dist-info/METADATA
xai_inference_engine-0.1.4.dist-info/WHEEL
xai_inference_engine-0.1.4.dist-info/top_level.txt
xai_inference_engine-0.1.4.dist-info/RECORD
