Metadata-Version: 2.1
Name: xai-inference-engine
Version: 0.1.4
Summary: A pip package for XAI Inferencing
Author: Ravidu Suien Rammuni Silva
Author-email: Ravidu Suien Rammuni Silva <ravidus@gmail.com>
Project-URL: Homepage, https://github.com/SuienS/xai-inference-engine
Project-URL: Bug Tracker, https://github.com/SuienS/xai-inference-engine/issues
Classifier: Programming Language :: Python :: 3
Classifier: License :: OSI Approved :: MIT License
Classifier: Operating System :: OS Independent
Requires-Python: >=3.7
License-File: LICENSE
